odoo/addons/sale_quick_commission/README.rst
odoo/addons/sale_quick_commission/__init__.py
odoo/addons/sale_quick_commission/__manifest__.py
odoo/addons/sale_quick_commission/i18n/es.po
odoo/addons/sale_quick_commission/i18n/it.po
odoo/addons/sale_quick_commission/i18n/pt_BR.po
odoo/addons/sale_quick_commission/i18n/sale_quick_commission.pot
odoo/addons/sale_quick_commission/models/__init__.py
odoo/addons/sale_quick_commission/models/product_mass_addition.py
odoo/addons/sale_quick_commission/readme/CONFIGURE.rst
odoo/addons/sale_quick_commission/readme/CONTRIBUTORS.rst
odoo/addons/sale_quick_commission/readme/DESCRIPTION.rst
odoo/addons/sale_quick_commission/readme/ROADMAP.rst
odoo/addons/sale_quick_commission/readme/USAGE.rst
odoo/addons/sale_quick_commission/static/description/icon.png
odoo/addons/sale_quick_commission/static/description/index.html
odoo14_addon_sale_quick_commission-14.0.1.0.1.dev10.dist-info/METADATA
odoo14_addon_sale_quick_commission-14.0.1.0.1.dev10.dist-info/WHEEL
odoo14_addon_sale_quick_commission-14.0.1.0.1.dev10.dist-info/top_level.txt
odoo14_addon_sale_quick_commission-14.0.1.0.1.dev10.dist-info/RECORD
